hashlist/__init__.py
hashlist/hashlist.py
hashlist_NickNackGus-1.0.0.dist-info/LICENSE
hashlist_NickNackGus-1.0.0.dist-info/METADATA
hashlist_NickNackGus-1.0.0.dist-info/WHEEL
hashlist_NickNackGus-1.0.0.dist-info/top_level.txt
hashlist_NickNackGus-1.0.0.dist-info/RECORD
