Metadata-Version: 2.1
Name: hashlist-NickNackGus
Version: 1.0.0
Summary: Compare differences in list order with minimal insertions/deletions
Home-page: https://github.com/NickNackGus/pyhashlist
Author: NickNackGus
Author-email: NickNackGus@gmail.com
License: UNKNOWN
Platform: UNKNOWN
Classifier: Programming Language :: Python :: 3
Classifier: License :: OSI Approved :: MIT License
Classifier: Operating System :: OS Independent
Requires-Dist: defaultdict-NickNackGus
